[
  {
    "allocator_high_water_bytes": 9233,
    "allocator_high_water_mb": 0.0,
    "allocator_live_bytes": 4579,
    "allocator_live_mb": 0.0,
    "clean_mmap_file_backed_estimate_bytes": null,
    "conclusion": "Windows process baseline before temporary schema copy",
    "named_owner_bytes": null,
    "peak_working_set_bytes": 5304320,
    "peak_working_set_mb": 5.1,
    "phase": "baseline_process_start",
    "private_bytes": 794624,
    "private_mb": 0.8,
    "working_set_bytes": 5304320,
    "working_set_mb": 5.1
  },
  {
    "allocator_high_water_bytes": 9233,
    "allocator_high_water_mb": 0.0,
    "allocator_live_bytes": 5749,
    "allocator_live_mb": 0.0,
    "clean_mmap_file_backed_estimate_bytes": null,
    "conclusion": "temporary committed schema bundle copied into isolated runtime dirs",
    "named_owner_bytes": null,
    "peak_working_set_bytes": 6307840,
    "peak_working_set_mb": 6.0,
    "phase": "after_temp_schema_copy",
    "private_bytes": 1019904,
    "private_mb": 1.0,
    "working_set_bytes": 6307840,
    "working_set_mb": 6.0
  },
  {
    "allocator_high_water_bytes": 9233,
    "allocator_high_water_mb": 0.0,
    "allocator_live_bytes": 7327,
    "allocator_live_mb": 0.0,
    "clean_mmap_file_backed_estimate_bytes": null,
    "conclusion": "RimeApi setup complete",
    "named_owner_bytes": null,
    "peak_working_set_bytes": 6541312,
    "peak_working_set_mb": 6.2,
    "phase": "after_setup",
    "private_bytes": 1019904,
    "private_mb": 1.0,
    "working_set_bytes": 6541312,
    "working_set_mb": 6.2
  },
  {
    "allocator_high_water_bytes": 9233,
    "allocator_high_water_mb": 0.0,
    "allocator_live_bytes": 7405,
    "allocator_live_mb": 0.0,
    "clean_mmap_file_backed_estimate_bytes": null,
    "conclusion": "RimeApi initialize complete",
    "named_owner_bytes": null,
    "peak_working_set_bytes": 6549504,
    "peak_working_set_mb": 6.2,
    "phase": "after_initialize",
    "private_bytes": 1019904,
    "private_mb": 1.0,
    "working_set_bytes": 6549504,
    "working_set_mb": 6.2
  },
  {
    "allocator_high_water_bytes": 435287742,
    "allocator_high_water_mb": 415.1,
    "allocator_live_bytes": 9303,
    "allocator_live_mb": 0.0,
    "clean_mmap_file_backed_estimate_bytes": null,
    "conclusion": "deploy reused prebuilt assets; create_session has not run",
    "named_owner_bytes": null,
    "peak_working_set_bytes": 508694528,
    "peak_working_set_mb": 485.1,
    "phase": "after_deploy",
    "private_bytes": 5947392,
    "private_mb": 5.7,
    "working_set_bytes": 14995456,
    "working_set_mb": 14.3
  },
  {
    "allocator_high_water_bytes": 435287742,
    "allocator_high_water_mb": 415.1,
    "allocator_live_bytes": 231209123,
    "allocator_live_mb": 220.5,
    "clean_mmap_file_backed_estimate_bytes": 15248382,
    "conclusion": "create_session loaded the workspace default schema",
    "named_owner_bytes": 177905176,
    "peak_working_set_bytes": 508694528,
    "peak_working_set_mb": 485.1,
    "phase": "after_create_session",
    "private_bytes": 298971136,
    "private_mb": 285.1,
    "working_set_bytes": 311566336,
    "working_set_mb": 297.1
  },
  {
    "allocator_high_water_bytes": 435287742,
    "allocator_high_water_mb": 415.1,
    "allocator_live_bytes": 200846815,
    "allocator_live_mb": 191.5,
    "clean_mmap_file_backed_estimate_bytes": 4640555,
    "conclusion": "select_schema applied requested active schema",
    "named_owner_bytes": 19774716,
    "peak_working_set_bytes": 508694528,
    "peak_working_set_mb": 485.1,
    "phase": "after_select_schema",
    "private_bytes": 298516480,
    "private_mb": 284.7,
    "working_set_bytes": 315805696,
    "working_set_mb": 301.2
  },
  {
    "allocator_high_water_bytes": 435287742,
    "allocator_high_water_mb": 415.1,
    "allocator_live_bytes": 200849847,
    "allocator_live_mb": 191.5,
    "clean_mmap_file_backed_estimate_bytes": 4640555,
    "conclusion": "realistic short Jyutping typing path",
    "named_owner_bytes": 19774716,
    "peak_working_set_bytes": 508694528,
    "peak_working_set_mb": 485.1,
    "phase": "after_typing_neihoumaa",
    "private_bytes": 298516480,
    "private_mb": 284.7,
    "working_set_bytes": 315822080,
    "working_set_mb": 301.2
  },
  {
    "allocator_high_water_bytes": 435287742,
    "allocator_high_water_mb": 415.1,
    "allocator_live_bytes": 200849914,
    "allocator_live_mb": 191.5,
    "clean_mmap_file_backed_estimate_bytes": 4640555,
    "conclusion": "steady sample after ESC clear",
    "named_owner_bytes": 19774716,
    "peak_working_set_bytes": 508694528,
    "peak_working_set_mb": 485.1,
    "phase": "steady_after_esc",
    "private_bytes": 298516480,
    "private_mb": 284.7,
    "working_set_bytes": 315822080,
    "working_set_mb": 301.2
  }
]